Workbook
Name NativeTimeline_fecha: #N/A
Name SegmentaciónDeDatos_categoria: #N/A

Sheet Dashboard (2)
B1: Dashboard de Ventas – Enero 2025
A3: KPI
A4: Ventas Totales | D4: =KPIs!B3 -> 10955.49 | Q4: Categoría
A5: Ventas por Categoría | D5: =KPIs!B4 -> Computo
A6: Producto más vendido | D6: =SUBSTITUTE(KPIs!B5,"AudÃ­fonos","Audífonos") -> Bluetooth Headphones
A7: Ticket Promedio | D7: =KPIs!B6 -> 365.183
A8: Inventario Total | D8: =KPIs!B7 -> 373
A9: Inventario Crítico (<20) | D9: =KPIs!B8 -> 23
A11: Mini resumen – Ene 2025
A12: Ventas totales | D12: =D4 -> 10955.49
A13: Categoría líder | D13: =D5 -> Computo
A14: SKUs críticos (<20) | D14: =D9 -> 23
A16: Insights y acciones – Enero 2025
A17: *Cómputo lidera ventas stock + bundles.
A18: *Audífonos BT top cross-sell laptops.
A19: *23 SKUs crítico reposición urgente.

Sheet ventas_dataset_nuevo
A1: date | B1: product | C1: category | D1: price | E1: quantity | F1: total revenue | G1: inventory | H1: revenue | I1: profit | J1: margin_pct
A2: 45658 | B2: Gaming Mouse | C2: Electronics | D2: 25.99 | E2: 2 | F2: 51.98 | G2: 34 | H2: =tbl_ventas[[#This Row],[price]]*tbl_ventas[[#This Row],[quantity]] -> 51.98 | I2: =tbl_ventas[[#This Row],[revenue]]-(tbl_ventas[[#This Row],[inventory]]*tbl_ventas[[#This Row],[quantity]]) -> -16.02 | J2: =tbl_ventas[[#This Row],[profit]]/tbl_ventas[[#This Row],[revenue]] -> -0.30819546
A3: 45658 | B3: Mechanical Keyboard | C3: Electronics | D3: 55.99 | E3: 1 | F3: 55.99 | G3: 12 | H3: =tbl_ventas[[#This Row],[price]]*tbl_ventas[[#This Row],[quantity]] -> 55.99 | I3: =tbl_ventas[[#This Row],[revenue]]-(tbl_ventas[[#This Row],[inventory]]*tbl_ventas[[#This Row],[quantity]]) -> 43.99 | J3: =tbl_ventas[[#This Row],[profit]]/tbl_ventas[[#This Row],[revenue]] -> 0.78567601
A4: 45659 | B4: Bluetooth Headphones | C4: Electronics | D4: 39.99 | E4: 3 | F4: 119.97 | G4: 20 | H4: =tbl_ventas[[#This Row],[price]]*tbl_ventas[[#This Row],[quantity]] -> 119.97 | I4: =tbl_ventas[[#This Row],[revenue]]-(tbl_ventas[[#This Row],[inventory]]*tbl_ventas[[#This Row],[quantity]]) -> 59.97 | J4: =tbl_ventas[[#This Row],[profit]]/tbl_ventas[[#This Row],[revenue]] -> 0.49987497
A5: 45659 | B5: Basic Laptop | C5: Computing | D5: 499.99 | E5: 1 | F5: 499.99 | G5: 5 | H5: =tbl_ventas[[#This Row],[price]]*tbl_ventas[[#This Row],[quantity]] -> 499.99 | I5: =tbl_ventas[[#This Row],[revenue]]-(tbl_ventas[[#This Row],[inventory]]*tbl_ventas[[#This Row],[quantity]]) -> 494.99 | J5: =tbl_ventas[[#This Row],[profit]]/tbl_ventas[[#This Row],[revenue]] -> 0.9899998
A6: 45660 | B6: Laptop Gamer | C6: Computing | D6: 1499.99 | E6: 1 | F6: 1499.99 | G6: 2 | H6: =tbl_ventas[[#This Row],[price]]*tbl_ventas[[#This Row],[quantity]] -> 1499.99 | I6: =tbl_ventas[[#This Row],[revenue]]-(tbl_ventas[[#This Row],[inventory]]*tbl_ventas[[#This Row],[quantity]]) -> 1497.99 | J6: =tbl_ventas[[#This Row],[profit]]/tbl_ventas[[#This Row],[revenue]] -> 0.99866666
A7: 45660 | B7: Gaming Mouse | C7: Electronics | D7: 25.99 | E7: 1 | F7: 25.99 | G7: 33 | H7: =tbl_ventas[[#This Row],[price]]*tbl_ventas[[#This Row],[quantity]] -> 25.99 | I7: =tbl_ventas[[#This Row],[revenue]]-(tbl_ventas[[#This Row],[inventory]]*tbl_ventas[[#This Row],[quantity]]) -> -7.01 | J7: =tbl_ventas[[#This Row],[profit]]/tbl_ventas[[#This Row],[revenue]] -> -0.26971912
A8: 45661 | B8: Mechanical Keyboard | C8: Electronics | D8: 55.99 | E8: 2 | F8: 111.98 | G8: 10 | H8: =tbl_ventas[[#This Row],[price]]*tbl_ventas[[#This Row],[quantity]] -> 111.98 | I8: =tbl_ventas[[#This Row],[revenue]]-(tbl_ventas[[#This Row],[inventory]]*tbl_ventas[[#This Row],[quantity]]) -> 91.98 | J8: =tbl_ventas[[#This Row],[profit]]/tbl_ventas[[#This Row],[revenue]] -> 0.82139668
A9: 45661 | B9: 24" Monitor | C9: Computing | D9: 129.99 | E9: 1 | F9: 129.99 | G9: 8 | H9: =tbl_ventas[[#This Row],[price]]*tbl_ventas[[#This Row],[quantity]] -> 129.99 | I9: =tbl_ventas[[#This Row],[revenue]]-(tbl_ventas[[#This Row],[inventory]]*tbl_ventas[[#This Row],[quantity]]) -> 121.99 | J9: =tbl_ventas[[#This Row],[profit]]/tbl_ventas[[#This Row],[revenue]] -> 0.9384568
A10: 45662 | B10: 10" Tablet | C10: Computing | D10: 199.99 | E10: 2 | F10: 399.98 | G10: 15 | H10: =tbl_ventas[[#This Row],[price]]*tbl_ventas[[#This Row],[quantity]] -> 399.98 | I10: =tbl_ventas[[#This Row],[revenue]]-(tbl_ventas[[#This Row],[inventory]]*tbl_ventas[[#This Row],[quantity]]) -> 369.98 | J10: =tbl_ventas[[#This Row],[profit]]/tbl_ventas[[#This Row],[revenue]] -> 0.92499625
A11: 45662 | B11: Bluetooth Headphones | C11: Electronics | D11: 39.99 | E11: 1 | F11: 39.99 | G11: 19 | H11: =tbl_ventas[[#This Row],[price]]*tbl_ventas[[#This Row],[quantity]] -> 39.99 | I11: =tbl_ventas[[#This Row],[revenue]]-(tbl_ventas[[#This Row],[inventory]]*tbl_ventas[[#This Row],[quantity]]) -> 20.99 | J11: =tbl_ventas[[#This Row],[profit]]/tbl_ventas[[#This Row],[revenue]] -> 0.52488122
A12: 45663 | B12: Basic Laptop | C12: Computing | D12: 499.99 | E12: 1 | F12: 499.99 | G12: 4 | H12: =tbl_ventas[[#This Row],[price]]*tbl_ventas[[#This Row],[quantity]] -> 499.99 | I12: =tbl_ventas[[#This Row],[revenue]]-(tbl_ventas[[#This Row],[inventory]]*tbl_ventas[[#This Row],[quantity]]) -> 495.99 | J12: =tbl_ventas[[#This Row],[profit]]/tbl_ventas[[#This Row],[revenue]] -> 0.99199984
A13: 45663 | B13: Gaming Mouse | C13: Electronics | D13: 25.99 | E13: 3 | F13: 77.97 | G13: 30 | H13: =tbl_ventas[[#This Row],[price]]*tbl_ventas[[#This Row],[quantity]] -> 77.97 | I13: =tbl_ventas[[#This Row],[revenue]]-(tbl_ventas[[#This Row],[inventory]]*tbl_ventas[[#This Row],[quantity]]) -> -12.03 | J13: =tbl_ventas[[#This Row],[profit]]/tbl_ventas[[#This Row],[revenue]] -> -0.15429011
... A31: 45672 | B31: Bluetooth Headphones | C31: Electronics | D31: 39.99 | E31: 2 | F31: 79.98 | G31: 11 | H31: =tbl_ventas[[#This Row],[price]]*tbl_ventas[[#This Row],[quantity]] -> 79.98 | I31: =tbl_ventas[[#This Row],[revenue]]-(tbl_ventas[[#This Row],[inventory]]*tbl_ventas[[#This Row],[quantity]]) -> 57.98 | J31: =tbl_ventas[[#This Row],[profit]]/tbl_ventas[[#This Row],[revenue]] -> 0.72493123

Sheet KPIs
A1: A | B1: B
A2: KPI
A3: Ventas Totales | B3: =SUMIFS(tbl_ventas[total revenue], tbl_ventas[date], ">=" & $B$10, tbl_ventas[date], "<=" & $B$11) -> 10955.49
A4: Categoría líder | B4: =TD_Ventas!A2 -> Computo
A5: Producto Más Vendido | B5: =INDEX(tbl_ventas[product], MATCH(MAX(tbl_ventas[quantity]), tbl_ventas[quantity], 0)) -> Bluetooth Headphones
A6: Ticket Promedio | B6: =IFERROR(B3 / COUNTIFS(tbl_ventas[date], ">=" & $B$10, tbl_ventas[date], "<=" & $B$11), 0) -> 365.183
A7: Inventario Total | B7: =SUM(tbl_ventas[inventory]) -> 373
A8: Inventario Crítico (<20) | B8: =COUNTIF(tbl_ventas[inventory], "<20") -> 23
A10: Fecha desde | B10: 45658
A11: Fecha hasta | B11: 45688

Sheet TD_Ventas
B1: Suma de ventas_totales
A2: Computo | B2: 9719.82
A3: Electrónica. | B3: 1235.67
A4: Total general | B4: 10955.49
A10: Etiquetas de fila | B10: Suma de ventas_totales
A11: 45658 | B11: 107.97
A12: 45659 | B12: 619.96
A13: 45660 | B13: 1525.98
A14: 45661 | B14: 241.97
A15: 45662 | B15: 439.97
A16: 45663 | B16: 577.96
A17: 45664 | B17: 1555.98
A18: 45665 | B18: 419.94
A19: 45666 | B19: 551.97
A20: 45667 | B20: 1611.97
A21: 45668 | B21: 329.98
A22: 45669 | B22: 579.97
... A25: 45672 | B25: 679.95
A26: Total general | B26: 10955.49
A30: Etiquetas de fila | B30: Suma de ventas_totales
A31: 45658 | B31: 107.97
A32: 45659 | B32: 619.96
A33: 45660 | B33: 1525.98
A34: 45661 | B34: 241.97
A35: 45662 | B35: 439.97
A36: 45663 | B36: 577.96
A37: 45664 | B37: 1555.98
A38: 45665 | B38: 419.94
A39: 45666 | B39: 551.97
A40: 45667 | B40: 1611.97
A41: 45668 | B41: 329.98
A42: 45669 | B42: 579.97
... A45: 45672 | B45: 679.95
A46: Total general | B46: 10955.49

Sheet Dashboard
A1: Dashboard de Ventas – Enero 2025
A3: KPI
A4: Ventas Totales | B4: =KPIs!B3 -> 10955.49
A5: Ventas por Categoría | B5: =KPIs!B4 -> Computo
A6: Producto más vendido | B6: =SUBSTITUTE(KPIs!B5,"AudÃ­fonos","Audífonos") -> Bluetooth Headphones
A7: Ticket Promedio | B7: =KPIs!B6 -> 365.183
A8: Inventario Total | B8: =KPIs!B7 -> 373
A9: Inventario Crítico (<20) | B9: =KPIs!B8 -> 23
B13: =B4 -> 10955.49
B15: =B5 -> Computo
B17: =B6 -> Bluetooth Headphones
B19: =B7 -> 365.183
B20: =B8 -> 373
B22: =B9 -> 23
