Workbook

Sheet Dashboard_EN
B1: Revenue & Profitability Dashboard — January 2025
A3: KPI
A4: Total Revenue | D4: =SUM(tbl_ventas[revenue]) -> 10955.49
A5: Computers | D5: Computers
A6: Best-Selling Product | D6: Headphones
A7: Average Ticket | D7: =SUM(tbl_ventas[revenue])/COUNTA(tbl_ventas[date]) -> 365.183
A8: Total Inventory | D8: =SUM(tbl_ventas[inventory]) -> 373
A9: Critical Inventory | D9: =COUNTIF(tbl_ventas[inventory],"<20") -> 23
A11: Quick Summary
A12: Total Revenue | D12: =D4 -> 10955.49
A13: Leading Category | D13: =D5 -> Computers
A14: Critical SKUs (<20) | D14: =D9 -> 23
A16: Key Insights & Actions — January 2025
A17: • Computers lead total sales and should be prioritized in stock and bundles.
A18: • Headphones show strong cross-sell potential with laptops.
A19: • 23 SKUs are below critical inventory levels and require urgent restocking.

Sheet dataset_clean
A1: date | B1: product | C1: category | D1: price | E1: quantity | F1: inventory | G1: revenue | H1: profit | I1: margin_pct
A2: 45658 | B2: Gaming Mouse | C2: ELECTRONICS | D2: 25.99 | E2: 2 | F2: 34 | G2: 51.98 | H2: -16.02 | I2: -0.30819546
A3: 45658 | B3: Mechanical Keyboard | C3: ELECTRONICS | D3: 55.99 | E3: 1 | F3: 12 | G3: 55.99 | H3: 43.99 | I3: 0.78567601
A4: 45659 | B4: Bluetooth Headphones | C4: ELECTRONICS | D4: 39.99 | E4: 3 | F4: 20 | G4: 119.97 | H4: 59.97 | I4: 0.49987497
A5: 45659 | B5: Basic Laptop | C5: COMPUTERS | D5: 499.99 | E5: 1 | F5: 5 | G5: 499.99 | H5: 494.99 | I5: 0.9899998
A6: 45660 | B6: Laptop Gamer | C6: COMPUTERS | D6: 1499.99 | E6: 1 | F6: 2 | G6: 1499.99 | H6: 1497.99 | I6: 0.99866666
A7: 45660 | B7: Gaming Mouse | C7: ELECTRONICS | D7: 25.99 | E7: 1 | F7: 33 | G7: 25.99 | H7: -7.01 | I7: -0.26971912
A8: 45661 | B8: Mechanical Keyboard | C8: ELECTRONICS | D8: 55.99 | E8: 2 | F8: 10 | G8: 111.98 | H8: 91.98 | I8: 0.82139668
A9: 45661 | B9: 24" Monitor | C9: COMPUTERS | D9: 129.99 | E9: 1 | F9: 8 | G9: 129.99 | H9: 121.99 | I9: 0.9384568
A10: 45662 | B10: 10" Tablet | C10: COMPUTERS | D10: 199.99 | E10: 2 | F10: 15 | G10: 399.98 | H10: 369.98 | I10: 0.92499625
A11: 45662 | B11: Bluetooth Headphones | C11: ELECTRONICS | D11: 39.99 | E11: 1 | F11: 19 | G11: 39.99 | H11: 20.99 | I11: 0.52488122
A12: 45663 | B12: Basic Laptop | C12: COMPUTERS | D12: 499.99 | E12: 1 | F12: 4 | G12: 499.99 | H12: 495.99 | I12: 0.99199984
A13: 45663 | B13: Gaming Mouse | C13: ELECTRONICS | D13: 25.99 | E13: 3 | F13: 30 | G13: 77.97 | H13: -12.03 | I13: -0.15429011
... A31: 45672 | B31: Bluetooth Headphones | C31: ELECTRONICS | D31: 39.99 | E31: 2 | F31: 11 | G31: 79.98 | H31: 57.98 | I31: 0.72493123

Sheet ventas_dataset_nuevo
A1: date | B1: product | C1: category | D1: price | E1: quantity | F1: inventory | G1: revenue | H1: profit | I1: margin_pct
A2: 45658 | B2: Gaming Mouse | C2: Electronics | D2: 25.99 | E2: 2 | F2: 34 | G2: =tbl_ventas[[#This Row],[price]]*tbl_ventas[[#This Row],[quantity]] -> 51.98 | H2: =tbl_ventas[[#This Row],[revenue]]-(tbl_ventas[[#This Row],[inventory]]*tbl_ventas[[#This Row],[quantity]]) -> -16.02 | I2: =IFERROR(tbl_ventas[[#This Row],[profit]]/tbl_ventas[[#This Row],[revenue]],0) -> -0.30819546
A3: 45658 | B3: Mechanical Keyboard | C3: Electronics | D3: 55.99 | E3: 1 | F3: 12 | G3: =tbl_ventas[[#This Row],[price]]*tbl_ventas[[#This Row],[quantity]] -> 55.99 | H3: =tbl_ventas[[#This Row],[revenue]]-(tbl_ventas[[#This Row],[inventory]]*tbl_ventas[[#This Row],[quantity]]) -> 43.99 | I3: =IFERROR(tbl_ventas[[#This Row],[profit]]/tbl_ventas[[#This Row],[revenue]],0) -> 0.78567601
A4: 45659 | B4: Bluetooth Headphones | C4: Electronics | D4: 39.99 | E4: 3 | F4: 20 | G4: =tbl_ventas[[#This Row],[price]]*tbl_ventas[[#This Row],[quantity]] -> 119.97 | H4: =tbl_ventas[[#This Row],[revenue]]-(tbl_ventas[[#This Row],[inventory]]*tbl_ventas[[#This Row],[quantity]]) -> 59.97 | I4: =IFERROR(tbl_ventas[[#This Row],[profit]]/tbl_ventas[[#This Row],[revenue]],0) -> 0.49987497
A5: 45659 | B5: Basic Laptop | C5: Computers | D5: 499.99 | E5: 1 | F5: 5 | G5: =tbl_ventas[[#This Row],[price]]*tbl_ventas[[#This Row],[quantity]] -> 499.99 | H5: =tbl_ventas[[#This Row],[revenue]]-(tbl_ventas[[#This Row],[inventory]]*tbl_ventas[[#This Row],[quantity]]) -> 494.99 | I5: =IFERROR(tbl_ventas[[#This Row],[profit]]/tbl_ventas[[#This Row],[revenue]],0) -> 0.9899998
A6: 45660 | B6: Laptop Gamer | C6: Computers | D6: 1499.99 | E6: 1 | F6: 2 | G6: =tbl_ventas[[#This Row],[price]]*tbl_ventas[[#This Row],[quantity]] -> 1499.99 | H6: =tbl_ventas[[#This Row],[revenue]]-(tbl_ventas[[#This Row],[inventory]]*tbl_ventas[[#This Row],[quantity]]) -> 1497.99 | I6: =IFERROR(tbl_ventas[[#This Row],[profit]]/tbl_ventas[[#This Row],[revenue]],0) -> 0.99866666
A7: 45660 | B7: Gaming Mouse | C7: Electronics | D7: 25.99 | E7: 1 | F7: 33 | G7: =tbl_ventas[[#This Row],[price]]*tbl_ventas[[#This Row],[quantity]] -> 25.99 | H7: =tbl_ventas[[#This Row],[revenue]]-(tbl_ventas[[#This Row],[inventory]]*tbl_ventas[[#This Row],[quantity]]) -> -7.01 | I7: =IFERROR(tbl_ventas[[#This Row],[profit]]/tbl_ventas[[#This Row],[revenue]],0) -> -0.26971912
A8: 45661 | B8: Mechanical Keyboard | C8: Electronics | D8: 55.99 | E8: 2 | F8: 10 | G8: =tbl_ventas[[#This Row],[price]]*tbl_ventas[[#This Row],[quantity]] -> 111.98 | H8: =tbl_ventas[[#This Row],[revenue]]-(tbl_ventas[[#This Row],[inventory]]*tbl_ventas[[#This Row],[quantity]]) -> 91.98 | I8: =IFERROR(tbl_ventas[[#This Row],[profit]]/tbl_ventas[[#This Row],[revenue]],0) -> 0.82139668
A9: 45661 | B9: 24" Monitor | C9: Computers | D9: 129.99 | E9: 1 | F9: 8 | G9: =tbl_ventas[[#This Row],[price]]*tbl_ventas[[#This Row],[quantity]] -> 129.99 | H9: =tbl_ventas[[#This Row],[revenue]]-(tbl_ventas[[#This Row],[inventory]]*tbl_ventas[[#This Row],[quantity]]) -> 121.99 | I9: =IFERROR(tbl_ventas[[#This Row],[profit]]/tbl_ventas[[#This Row],[revenue]],0) -> 0.9384568
A10: 45662 | B10: 10" Tablet | C10: Computers | D10: 199.99 | E10: 2 | F10: 15 | G10: =tbl_ventas[[#This Row],[price]]*tbl_ventas[[#This Row],[quantity]] -> 399.98 | H10: =tbl_ventas[[#This Row],[revenue]]-(tbl_ventas[[#This Row],[inventory]]*tbl_ventas[[#This Row],[quantity]]) -> 369.98 | I10: =IFERROR(tbl_ventas[[#This Row],[profit]]/tbl_ventas[[#This Row],[revenue]],0) -> 0.92499625
A11: 45662 | B11: Bluetooth Headphones | C11: Electronics | D11: 39.99 | E11: 1 | F11: 19 | G11: =tbl_ventas[[#This Row],[price]]*tbl_ventas[[#This Row],[quantity]] -> 39.99 | H11: =tbl_ventas[[#This Row],[revenue]]-(tbl_ventas[[#This Row],[inventory]]*tbl_ventas[[#This Row],[quantity]]) -> 20.99 | I11: =IFERROR(tbl_ventas[[#This Row],[profit]]/tbl_ventas[[#This Row],[revenue]],0) -> 0.52488122
A12: 45663 | B12: Basic Laptop | C12: Computers | D12: 499.99 | E12: 1 | F12: 4 | G12: =tbl_ventas[[#This Row],[price]]*tbl_ventas[[#This Row],[quantity]] -> 499.99 | H12: =tbl_ventas[[#This Row],[revenue]]-(tbl_ventas[[#This Row],[inventory]]*tbl_ventas[[#This Row],[quantity]]) -> 495.99 | I12: =IFERROR(tbl_ventas[[#This Row],[profit]]/tbl_ventas[[#This Row],[revenue]],0) -> 0.99199984
A13: 45663 | B13: Gaming Mouse | C13: Electronics | D13: 25.99 | E13: 3 | F13: 30 | G13: =tbl_ventas[[#This Row],[price]]*tbl_ventas[[#This Row],[quantity]] -> 77.97 | H13: =tbl_ventas[[#This Row],[revenue]]-(tbl_ventas[[#This Row],[inventory]]*tbl_ventas[[#This Row],[quantity]]) -> -12.03 | I13: =IFERROR(tbl_ventas[[#This Row],[profit]]/tbl_ventas[[#This Row],[revenue]],0) -> -0.15429011
... A31: 45672 | B31: Bluetooth Headphones | C31: Electronics | D31: 39.99 | E31: 2 | F31: 11 | G31: =tbl_ventas[[#This Row],[price]]*tbl_ventas[[#This Row],[quantity]] -> 79.98 | H31: =tbl_ventas[[#This Row],[revenue]]-(tbl_ventas[[#This Row],[inventory]]*tbl_ventas[[#This Row],[quantity]]) -> 57.98 | I31: =IFERROR(tbl_ventas[[#This Row],[profit]]/tbl_ventas[[#This Row],[revenue]],0) -> 0.72493123

Sheet KPIs
A1: A | B1: B
A2: KPI
A3: Total Revenue | B3: =SUM(tbl_ventas[revenue]) -> 10955.49
A4: Leading Category | B4: Computers
A5: Best-Selling Product | B5: Bluetooth Headphones | C5: =_xlfn.XLOOKUP(B5,tbl_ventas[product],tbl_ventas[price]) -> 39.99
A6: Average Ticket | B6: =AVERAGE(tbl_ventas[revenue]) -> 365.183
A7: Total Inventory | B7: =SUM(tbl_ventas[inventory]) -> 373
A8: Critical Inventory (<20) | B8: =COUNTIF(tbl_ventas[inventory], "<20") -> 23
A10: From Date | B10: 45658
A11: To Date | B11: 45688
A13: Revenue Electronics | B13: =SUMIFS(tbl_ventas[revenue],tbl_ventas[category],"Electronics",tbl_ventas[date],">="&$B$10,tbl_ventas[date],"<="&$B$11) -> 1235.67
A14: Revenue Computers | B14: =SUMIFS(tbl_ventas[revenue],tbl_ventas[category],"Computers",tbl_ventas[date],">="&$B$10,tbl_ventas[date],"<="&$B$11) -> 9719.82
A15: Profit Electronics | B15: =SUMIFS(tbl_ventas[profit],tbl_ventas[category],"Electronics",tbl_ventas[date],">="&$B$10,tbl_ventas[date],"<="&$B$11) -> 597.67
A16: Profit Computers | B16: =SUMIFS(tbl_ventas[profit],tbl_ventas[category],"Computers",tbl_ventas[date],">="&$B$10,tbl_ventas[date],"<="&$B$11) -> 9600.82
A17: Margin Electronics | B17: =AVERAGEIFS(tbl_ventas[margin_pct],tbl_ventas[category],"Electronics",tbl_ventas[date],">="&$B$10,tbl_ventas[date],"<="&$B$11) -> 0.41072067
A18: Margin Computers | B18: =AVERAGEIFS(tbl_ventas[margin_pct],tbl_ventas[category],"Computers",tbl_ventas[date],">="&$B$10,tbl_ventas[date],"<="&$B$11) -> 0.97313031

Sheet TD_Ventas
A10: Date | B10: Daily Revenue
A11: 45658 | B11: 107.97
A12: 45659 | B12: 619.96
A13: 45660 | B13: 1525.98
A14: 45661 | B14: 241.97
A15: 45662 | B15: 439.97
A16: 45663 | B16: 577.96
A17: 45664 | B17: 1555.98
A18: 45665 | B18: 419.94
A19: 45666 | B19: 551.97
A20: 45667 | B20: 1611.97
A21: 45668 | B21: 329.98
A22: 45669 | B22: 579.97
... A25: 45672 | B25: 679.95
A26: Grand Total | B26: 10955.49

Sheet Dashboard_ES
A1: Dashboard de Ventas – Enero 2025
A3: KPI
A4: Ventas Totales | B4: =KPIs!B3 -> 10955.49
A5: Ventas por Categoría | B5: =KPIs!B4 -> Computers
A6: Producto más vendido | B6: =SUBSTITUTE(KPIs!B5,"AudÃ­fonos","Audífonos") -> Bluetooth Headphones
A7: Ticket Promedio | B7: =KPIs!B6 -> 365.183
A8: Inventario Total | B8: =KPIs!B7 -> 373
A9: Inventario Crítico (<20) | B9: =KPIs!B8 -> 23
B13: =B4 -> 10955.49
B15: =B5 -> Computers
B17: =B6 -> Bluetooth Headphones
B19: =B7 -> 365.183
B20: =B8 -> 373
B22: =B9 -> 23
